finsets/__init__.py
finsets/_modidx.py
finsets/cli.py
finsets/fetch_tools.py
finsets/fred/__init__.py
finsets/fred/fred.py
finsets/fred/fred_api.py
finsets/papers/__init__.py
finsets/papers/dickerson_etal_2023.py
finsets/papers/gilchrist_zakrajsek_2012.py
finsets/papers/gurkaynak_etal_2007.py
finsets/papers/hassan_etal_2019.py
finsets/papers/hoberg_phillips_2010.py
finsets/papers/peters_taylor_2016.py
finsets/wrds/__init__.py
finsets/wrds/bondret.py
finsets/wrds/compa.py
finsets/wrds/compa_ccm.py
finsets/wrds/compq.py
finsets/wrds/compq_ccm.py
finsets/wrds/crspd.py
finsets/wrds/crspm.py
finsets/wrds/ibes_ltg.py
finsets/wrds/linking.py
finsets/wrds/mergent.py
finsets/wrds/ratios.py
finsets/wrds/wrds_api.py
finsets-0.0.6.dist-info/licenses/LICENSE
finsets-0.0.6.dist-info/METADATA
finsets-0.0.6.dist-info/WHEEL
finsets-0.0.6.dist-info/entry_points.txt
finsets-0.0.6.dist-info/top_level.txt
finsets-0.0.6.dist-info/RECORD
