Metadata-Version: 2.4
Name: finsets
Version: 0.0.6
Summary: Download and process datasets commonly used in finance research
Home-page: https://github.com/ionmihai/finsets
Author: Mihai Ion
Author-email: mihaiion@email.arizona.edu
License: Apache Software License 2.0
Keywords: nbdev jupyter notebook python
Classifier: Development Status :: 4 - Beta
Classifier: Intended Audience :: Developers
Classifier: Natural Language :: English
Classifier: Programming Language :: Python :: 3.7
Classifier: Programming Language :: Python :: 3.8
Classifier: Programming Language :: Python :: 3.9
Classifier: Programming Language :: Python :: 3.10
Classifier: License :: OSI Approved :: Apache Software License
Requires-Python: >=3.7
License-File: LICENSE
Requires-Dist: fastcore
Requires-Dist: pandas
Requires-Dist: scipy
Requires-Dist: numpy
Requires-Dist: requests
Requires-Dist: psycopg2-binary
Requires-Dist: wrds
Requires-Dist: estout
Requires-Dist: pandasmore
Requires-Dist: thefuzz
Requires-Dist: python-Levenshtein
Provides-Extra: dev
Dynamic: author
Dynamic: author-email
Dynamic: classifier
Dynamic: description
Dynamic: description-content-type
Dynamic: home-page
Dynamic: keywords
Dynamic: license
Dynamic: license-file
Dynamic: provides-extra
Dynamic: requires-dist
Dynamic: requires-python
Dynamic: summary
